dynamo_wrapper/__init__.py
dynamo_wrapper/client.py
dynamo_wrapper/exceptions.py
dynamo_wrapper/table.py
dynamo_wrapper-0.1.1.dist-info/LICENSE
dynamo_wrapper-0.1.1.dist-info/METADATA
dynamo_wrapper-0.1.1.dist-info/WHEEL
dynamo_wrapper-0.1.1.dist-info/top_level.txt
dynamo_wrapper-0.1.1.dist-info/RECORD
