Metadata-Version: 2.1
Name: dynamo-wrapper
Version: 0.1.1
Summary: A PyMongo-like wrapper for DynamoDB
Home-page: https://github.com/hcevikGA/dynamo-wrapper
Author: Huseyin Cevik
Author-email: huseyin.cevik@outlook.de
Classifier: Programming Language :: Python :: 3
Classifier: Programming Language :: Python :: 3.6
Classifier: Programming Language :: Python :: 3.7
Classifier: Programming Language :: Python :: 3.8
Classifier: Programming Language :: Python :: 3.9
Classifier: License :: OSI Approved :: MIT License
Classifier: Operating System :: OS Independent
Classifier: Intended Audience :: Developers
Classifier: Topic :: Database
Classifier: Topic :: Software Development :: Libraries :: Python Modules
Requires-Python: >=3.6
License-File: LICENSE
Requires-Dist: boto3 >=1.17.0
Requires-Dist: botocore >=1.20.0
Provides-Extra: dev
Requires-Dist: moto >=2.0.0 ; extra == 'dev'
Requires-Dist: pytest >=6.0.0 ; extra == 'dev'
